gmpyinfr/__init__.py
gmpyinfr/utils/__init__.py
gmpyinfr-0.0.3.dist-info/LICENSE
gmpyinfr-0.0.3.dist-info/METADATA
gmpyinfr-0.0.3.dist-info/WHEEL
gmpyinfr-0.0.3.dist-info/top_level.txt
gmpyinfr-0.0.3.dist-info/RECORD
