Metadata-Version: 2.1
Name: gmpyinfr
Version: 0.0.3
Summary: Infraestrutura basica python de uma equipe de Ciencia de Dados
Home-page: UNKNOWN
Author: Alex Newman
Author-email: a.newmanvs@gmail.com
License: UNKNOWN
Platform: UNKNOWN
Classifier: Development Status :: 5 - Production/Stable
Classifier: Environment :: Console
Classifier: Programming Language :: Python
Classifier: Programming Language :: Python :: 3
Classifier: Programming Language :: Python :: 3 :: Only
Classifier: Programming Language :: Python :: 3.7
Classifier: Operating System :: Unix
Requires-Python: >=3.6
Requires-Dist: numpy (>=1.16.5)
Requires-Dist: pandas (>=1.0.0)
Requires-Dist: pyarrow (>=3.0.0)
Provides-Extra: all
Requires-Dist: gmpyinfr-dbutils (>=0.0.7) ; extra == 'all'
Requires-Dist: gmpyinfr-telegram (>=0.0.4) ; extra == 'all'
Requires-Dist: gmpyinfr-amqp (>=0.0.2) ; extra == 'all'
Requires-Dist: gmpyinfr-log (>=0.0.1) ; extra == 'all'
Provides-Extra: amqp
Requires-Dist: gmpyinfr-amqp (>=0.0.2) ; extra == 'amqp'
Provides-Extra: bot
Requires-Dist: gmpyinfr-telegram (>=0.0.4) ; extra == 'bot'
Provides-Extra: db
Requires-Dist: gmpyinfr-dbutils (>=0.0.7) ; extra == 'db'
Provides-Extra: log
Requires-Dist: gmpyinfr-log (>=0.0.1) ; extra == 'log'
